correxit/__init__.py
correxit/_version.py
correxit/handlers.py
correxit/labextension/package.json
correxit/labextension/schemas/correxit/package.json.orig
correxit/labextension/schemas/correxit/plugin.json
correxit/labextension/static/675.852a5f31db43538e7061.js
correxit/labextension/static/728.01a08fcc28d4d2979e5b.js
correxit/labextension/static/remoteEntry.f6ec01de78b774b84c1a.js
correxit/labextension/static/style.js
correxit/labextension/static/third-party-licenses.json
correxit/tests/__init__.py
correxit/tests/test_handlers.py
correxit-0.1.0.data/data/etc/jupyter/jupyter_server_config.d/correxit.json
correxit-0.1.0.data/data/share/jupyter/labextensions/correxit/package.json
correxit-0.1.0.data/data/share/jupyter/labextensions/correxit/schemas/correxit/package.json.orig
correxit-0.1.0.data/data/share/jupyter/labextensions/correxit/schemas/correxit/plugin.json
correxit-0.1.0.data/data/share/jupyter/labextensions/correxit/static/675.852a5f31db43538e7061.js
correxit-0.1.0.data/data/share/jupyter/labextensions/correxit/static/728.01a08fcc28d4d2979e5b.js
correxit-0.1.0.data/data/share/jupyter/labextensions/correxit/static/remoteEntry.f6ec01de78b774b84c1a.js
correxit-0.1.0.data/data/share/jupyter/labextensions/correxit/static/style.js
correxit-0.1.0.data/data/share/jupyter/labextensions/correxit/static/third-party-licenses.json
correxit-0.1.0.data/data/share/jupyter/labextensions/correxit/install.json
correxit-0.1.0.dist-info/METADATA
correxit-0.1.0.dist-info/WHEEL
correxit-0.1.0.dist-info/licenses/LICENSE
correxit-0.1.0.dist-info/RECORD
