Metadata-Version: 2.4
Name: correxit
Version: 0.1.0
Summary: correxit is a JupyterLab extension and the third-person singular perfect active indicative conjugation of the Latin verb corrigere
Project-URL: Homepage, https://github.com/notebook-link/correxit
Project-URL: Bug Tracker, https://github.com/notebook-link/correxit/issues
Project-URL: Repository, https://github.com/notebook-link/correxit.git
Author-email: "A. T. Darian" <correxit@darian.link>
License: Copyright (c) 2025, A. T. Darian
License-File: LICENSE
Keywords: jupyter,jupyterlab,jupyterlab-extension
Classifier: Framework :: Jupyter
Classifier: Framework :: Jupyter :: JupyterLab
Classifier: Framework :: Jupyter :: JupyterLab :: 4
Classifier: Framework :: Jupyter :: JupyterLab :: Extensions
Classifier: Framework :: Jupyter :: JupyterLab :: Extensions :: Prebuilt
Classifier: Programming Language :: Python
Classifier: Programming Language :: Python :: 3
Classifier: Programming Language :: Python :: 3.9
Classifier: Programming Language :: Python :: 3.10
Classifier: Programming Language :: Python :: 3.11
Classifier: Programming Language :: Python :: 3.12
Classifier: Programming Language :: Python :: 3.13
Requires-Python: >=3.9
Requires-Dist: jupyter-server<3,>=2.4.0
Provides-Extra: test
Requires-Dist: coverage; extra == 'test'
Requires-Dist: pytest; extra == 'test'
Requires-Dist: pytest-asyncio; extra == 'test'
Requires-Dist: pytest-cov; extra == 'test'
Requires-Dist: pytest-jupyter[server]>=0.6.0; extra == 'test'
